{"trial_id": "0056", "hyperparameters": {"space": [{"class_name": "Choice", "config": {"name": "activation", "default": "relu", "conditions": [], "values": ["relu", "elu"], "ordered": false}}, {"class_name": "Int", "config": {"name": "units_0", "default": null, "conditions": [], "min_value": 50, "max_value": 151, "step": 50, "sampling": null}}, {"class_name": "Int", "config": {"name": "num_layers", "default": null, "conditions": [], "min_value": 1, "max_value": 3, "step": 1, "sampling": null}}, {"class_name": "Int", "config": {"name": "units_1", "default": null, "conditions": [], "min_value": 50, "max_value": 151, "step": 50, "sampling": null}}], "values": {"activation": "relu", "units_0": 100, "num_layers": 3, "units_1": 50, "tuner/epochs": 20, "tuner/initial_epoch": 0, "tuner/bracket": 0, "tuner/round": 0}}, "metrics": {"metrics": {"loss": {"direction": "min", "observations": [{"value": [0.5430610179901123], "step": 10}]}, "accuracy": {"direction": "max", "observations": [{"value": [0.7336339354515076], "step": 10}]}, "val_loss": {"direction": "min", "observations": [{"value": [0.5468137264251709], "step": 10}]}, "val_accuracy": {"direction": "max", "observations": [{"value": [0.7362099289894104], "step": 10}]}}}, "score": 0.7362099289894104, "best_step": 10, "status": "COMPLETED"}