{"trial_id": "0058", "hyperparameters": {"space": [{"class_name": "Choice", "config": {"name": "activation", "default": "relu", "conditions": [], "values": ["relu", "elu"], "ordered": false}}, {"class_name": "Int", "config": {"name": "units_0", "default": null, "conditions": [], "min_value": 50, "max_value": 151, "step": 50, "sampling": null}}, {"class_name": "Int", "config": {"name": "num_layers", "default": null, "conditions": [], "min_value": 1, "max_value": 3, "step": 1, "sampling": null}}, {"class_name": "Int", "config": {"name": "units_1", "default": null, "conditions": [], "min_value": 50, "max_value": 151, "step": 50, "sampling": null}}], "values": {"activation": "elu", "units_0": 150, "num_layers": 1, "units_1": 100, "tuner/epochs": 20, "tuner/initial_epoch": 0, "tuner/bracket": 0, "tuner/round": 0}}, "metrics": {"metrics": {"loss": {"direction": "min", "observations": [{"value": [0.5532203912734985], "step": 7}]}, "accuracy": {"direction": "max", "observations": [{"value": [0.7277639508247375], "step": 7}]}, "val_loss": {"direction": "min", "observations": [{"value": [0.5537043809890747], "step": 7}]}, "val_accuracy": {"direction": "max", "observations": [{"value": [0.7322449088096619], "step": 7}]}}}, "score": 0.7322449088096619, "best_step": 7, "status": "COMPLETED"}